conc_nouns/__init__.py
conc_nouns/__main__.py
conc_nouns/conc_nouns.py
conc_nouns-0.1.0.dist-info/entry_points.txt
conc_nouns-0.1.0.dist-info/LICENSE
conc_nouns-0.1.0.dist-info/WHEEL
conc_nouns-0.1.0.dist-info/METADATA
conc_nouns-0.1.0.dist-info/RECORD
